{
  "generator-jhipster": {
    "applicationType": "monolith",
    "gitCompany": "",
    "baseName": "jhipsterTask",
    "packageName": "com.seneau.task",
    "packageFolder": "com/seneau/task",
    "serverPort": 8085,
    "serviceDiscoveryType": false,
    "authenticationType": "jwt",
    "uaaBaseName": "../uaa",
    "cacheProvider": "ehcache",
    "enableHibernateCache": false,
    "websocket": false,
    "databaseType": "sql",
    "devDatabaseType": "h2Disk",
    "prodDatabaseType": "mysql",
    "searchEngine": false,
    "enableSwaggerCodegen": false,
    "messageBroker": false,
    "buildTool": "maven",
    "useSass": true,
    "clientPackageManager": "npm",
    "testFrameworks": ["gatling"],
    "enableTranslation": true,
    "nativeLanguage": "fr",
    "languages": ["en", "fr"],
    "clientFramework": "angularX",
    "jhiPrefix": "jhi",
    "jhipsterVersion": "6.10.5",
    "jwtSecretKey": "OWQyMDQyOWQ4MzVlYzFhMzY2NGUxZGZmZDczY2NjMTBlN2NiMWU0YzVmYjhlOWJiMmZmZjlkMTU4YmZlOWM5ZWVhNWE3NmYwODA2ODYxMmUwZTU3ZDM5MDA1OTVjY2I2NWUyMjUzMDcyZTYxYzYwOTcwMWRkMWI4MmJhYjg3MGQ=",
    "embeddableLaunchScript": false,
    "clientTheme": "none",
    "creationTimestamp": 1609143324190,
    "entitySuffix": "",
    "dtoSuffix": "DTO",
    "otherModules": [],
    "blueprints": [],
    "prettierJava": true
  },
  "git-provider": "GitHub",
  "git-company": "laye-lab",
  "repository-name": "jhipsterTask"
}
